[
  {
    "appId": "207230",
    "title": "archeblade",
    "timestamp": 1536065252,
    "rating": "Borked",
    "notes": "after letting steam install the important software for the game just crash",
    "os": "Ubuntu 18.04",
    "gpuDriver": "NVIDIA 396.51",
    "specs": "Ryzen 5 1600 / GTX 970",
    "protonVersion": "Default"
  },
  {
    "appId": "207230",
    "title": "Archeblade",
    "timestamp": 1536193210,
    "rating": "Borked",
    "notes": "Crashes at start",
    "os": "Fedora 28",
    "gpuDriver": "NVIDIA 396.54",
    "specs": "GTX 1050 Ti",
    "protonVersion": "3.7-5"
  }
]